[
  {
    "name": "v4Guard Checkpoint",
    "category": "Captcha",
    "confidence": "high",
    "domain_signatures": [],
    "html_signatures": [],
    "script_url_signatures": [
      "v4guard.io/checkpoint"
    ],
    "js_asset_signatures": [],
    "package_url_signatures": [],
    "stylesheet_url_signatures": [],
    "meta_generator_signatures": [],
    "dom_marker_signatures": [],
    "cookie_signatures": [],
    "header_signatures": {}
  },
  {
    "name": "Vaadin",
    "category": "Web Framework",
    "confidence": "high",
    "domain_signatures": [],
    "html_signatures": [],
    "script_url_signatures": [
      "vaadinBootstrap.js"
    ],
    "js_asset_signatures": [],
    "package_url_signatures": [],
    "stylesheet_url_signatures": [],
    "meta_generator_signatures": [],
    "dom_marker_signatures": [],
    "cookie_signatures": [],
    "header_signatures": {}
  },
  {
    "name": "ValueCommerce",
    "category": "Affiliate Program",
    "confidence": "high",
    "domain_signatures": [],
    "html_signatures": [
      "ap.valuecommerce.com"
    ],
    "script_url_signatures": [
      "valuecommerce.com"
    ],
    "js_asset_signatures": [],
    "package_url_signatures": [],
    "stylesheet_url_signatures": [],
    "meta_generator_signatures": [],
    "dom_marker_signatures": [],
    "cookie_signatures": [],
    "header_signatures": {}
  },
  {
    "name": "Vanco Payment Solutions",
    "category": "Other",
    "confidence": "high",
    "domain_signatures": [],
    "html_signatures": [
      "eservicepayments.com"
    ],
    "script_url_signatures": [
      "eservicepayments.com"
    ],
    "js_asset_signatures": [],
    "package_url_signatures": [],
    "stylesheet_url_signatures": [],
    "meta_generator_signatures": [],
    "dom_marker_signatures": [],
    "cookie_signatures": [],
    "header_signatures": {}
  },
  {
    "name": "Vanilla",
    "category": "Forum",
    "confidence": "high",
    "domain_signatures": [],
    "html_signatures": [
      "<body id=\"DiscussionsPage\"",
      "<body id=\"vanilla\""
    ],
    "script_url_signatures": [],
    "js_asset_signatures": [],
    "package_url_signatures": [],
    "stylesheet_url_signatures": [],
    "meta_generator_signatures": [],
    "dom_marker_signatures": [],
    "cookie_signatures": [],
    "header_signatures": {
      "x-powered-by": [
        "Vanilla"
      ]
    }
  },
  {
    "name": "Vant",
    "category": "UI Framework",
    "confidence": "high",
    "domain_signatures": [],
    "html_signatures": [],
    "script_url_signatures": [],
    "js_asset_signatures": [
      "vant.version"
    ],
    "package_url_signatures": [],
    "stylesheet_url_signatures": [
      "npm/vant"
    ],
    "meta_generator_signatures": [],
    "dom_marker_signatures": [],
    "cookie_signatures": [],
    "header_signatures": {}
  },
  {
    "name": "VAPTCHA",
    "category": "Captcha",
    "confidence": "high",
    "domain_signatures": [],
    "html_signatures": [],
    "script_url_signatures": [
      "vaptcha.com/v"
    ],
    "js_asset_signatures": [],
    "package_url_signatures": [],
    "stylesheet_url_signatures": [],
    "meta_generator_signatures": [],
    "dom_marker_signatures": [],
    "cookie_signatures": [],
    "header_signatures": {}
  },
  {
    "name": "Varbase",
    "category": "CMS",
    "confidence": "medium",
    "domain_signatures": [],
    "html_signatures": [],
    "script_url_signatures": [],
    "js_asset_signatures": [
      "drupalSettings.ajaxPageState.libraries"
    ],
    "package_url_signatures": [],
    "stylesheet_url_signatures": [],
    "meta_generator_signatures": [],
    "dom_marker_signatures": [
      "_varbase",
      "block-varbase",
      "varbase-",
      "varbase_"
    ],
    "cookie_signatures": [],
    "header_signatures": {}
  },
  {
    "name": "Varnish",
    "category": "Caching",
    "confidence": "medium",
    "domain_signatures": [],
    "html_signatures": [],
    "script_url_signatures": [],
    "js_asset_signatures": [],
    "package_url_signatures": [],
    "stylesheet_url_signatures": [],
    "meta_generator_signatures": [],
    "dom_marker_signatures": [],
    "cookie_signatures": [
      "ssr-caching"
    ],
    "header_signatures": {
      "server-timing": [
        "varnish"
      ],
      "via": [
        "varnish"
      ]
    }
  },
  {
    "name": "vcita",
    "category": "Live Chat",
    "confidence": "high",
    "domain_signatures": [],
    "html_signatures": [
      "www.vcita.com/widgets"
    ],
    "script_url_signatures": [
      "widgets.vcdnita.com",
      "www.vcita.com/widgets"
    ],
    "js_asset_signatures": [
      "LiveSite.btCheckout"
    ],
    "package_url_signatures": [],
    "stylesheet_url_signatures": [],
    "meta_generator_signatures": [],
    "dom_marker_signatures": [],
    "cookie_signatures": [],
    "header_signatures": {}
  },
  {
    "name": "VDX.tv",
    "category": "Advertising",
    "confidence": "high",
    "domain_signatures": [],
    "html_signatures": [],
    "script_url_signatures": [
      "exponential.com",
      "tribalfusion.com"
    ],
    "js_asset_signatures": [],
    "package_url_signatures": [],
    "stylesheet_url_signatures": [
      "exponential.com",
      "tribalfusion.com"
    ],
    "meta_generator_signatures": [],
    "dom_marker_signatures": [],
    "cookie_signatures": [],
    "header_signatures": {}
  },
  {
    "name": "Ve Global",
    "category": "Analytics",
    "confidence": "medium",
    "domain_signatures": [],
    "html_signatures": [],
    "script_url_signatures": [],
    "js_asset_signatures": [
      "veTagData.appsServicesUrl"
    ],
    "package_url_signatures": [],
    "stylesheet_url_signatures": [],
    "meta_generator_signatures": [],
    "dom_marker_signatures": [],
    "cookie_signatures": [],
    "header_signatures": {}
  },
  {
    "name": "Vectary",
    "category": "Other",
    "confidence": "medium",
    "domain_signatures": [],
    "html_signatures": [
      "app.vectary.com"
    ],
    "script_url_signatures": [],
    "js_asset_signatures": [],
    "package_url_signatures": [],
    "stylesheet_url_signatures": [],
    "meta_generator_signatures": [],
    "dom_marker_signatures": [],
    "cookie_signatures": [],
    "header_signatures": {}
  },
  {
    "name": "Vendre",
    "category": "Ecommerce",
    "confidence": "medium",
    "domain_signatures": [],
    "html_signatures": [],
    "script_url_signatures": [],
    "js_asset_signatures": [
      "vendre_config",
      "VendreMap.maps_loaded"
    ],
    "package_url_signatures": [],
    "stylesheet_url_signatures": [],
    "meta_generator_signatures": [],
    "dom_marker_signatures": [],
    "cookie_signatures": [],
    "header_signatures": {}
  },
  {
    "name": "Venmo",
    "category": "Payment Processor",
    "confidence": "medium",
    "domain_signatures": [],
    "html_signatures": [
      "pi-venmo"
    ],
    "script_url_signatures": [],
    "js_asset_signatures": [],
    "package_url_signatures": [],
    "stylesheet_url_signatures": [],
    "meta_generator_signatures": [],
    "dom_marker_signatures": [],
    "cookie_signatures": [],
    "header_signatures": {}
  },
  {
    "name": "VentryShield",
    "category": "Captcha",
    "confidence": "high",
    "domain_signatures": [],
    "html_signatures": [],
    "script_url_signatures": [],
    "js_asset_signatures": [],
    "package_url_signatures": [],
    "stylesheet_url_signatures": [],
    "meta_generator_signatures": [],
    "dom_marker_signatures": [],
    "cookie_signatures": [
      "ventryshield_pre"
    ],
    "header_signatures": {
      "x-ventryshield-cache-status": [
        "no-cache"
      ]
    }
  },
  {
    "name": "Veoxa",
    "category": "Advertising",
    "confidence": "high",
    "domain_signatures": [],
    "html_signatures": [],
    "script_url_signatures": [
      "tracking.veoxa.com"
    ],
    "js_asset_signatures": [
      "VuVeoxaContent"
    ],
    "package_url_signatures": [],
    "stylesheet_url_signatures": [],
    "meta_generator_signatures": [],
    "dom_marker_signatures": [],
    "cookie_signatures": [],
    "header_signatures": {}
  },
  {
    "name": "Vercel Analytics",
    "category": "Analytics",
    "confidence": "high",
    "domain_signatures": [],
    "html_signatures": [],
    "script_url_signatures": [
      "_vercel/insights/script.js",
      "va/script.js"
    ],
    "js_asset_signatures": [],
    "package_url_signatures": [],
    "stylesheet_url_signatures": [],
    "meta_generator_signatures": [],
    "dom_marker_signatures": [],
    "cookie_signatures": [],
    "header_signatures": {}
  },
  {
    "name": "Vercel Speed Insights",
    "category": "Analytics",
    "confidence": "high",
    "domain_signatures": [],
    "html_signatures": [],
    "script_url_signatures": [
      "_vercel/speed-insights/script.js"
    ],
    "js_asset_signatures": [],
    "package_url_signatures": [],
    "stylesheet_url_signatures": [],
    "meta_generator_signatures": [],
    "dom_marker_signatures": [
      "@vercel/speed-insights/next"
    ],
    "cookie_signatures": [],
    "header_signatures": {}
  },
  {
    "name": "Verifone 2Checkout",
    "category": "Payment Processor",
    "confidence": "high",
    "domain_signatures": [],
    "html_signatures": [],
    "script_url_signatures": [],
    "js_asset_signatures": [],
    "package_url_signatures": [],
    "stylesheet_url_signatures": [
      "2checkout.com"
    ],
    "meta_generator_signatures": [],
    "dom_marker_signatures": [],
    "cookie_signatures": [],
    "header_signatures": {}
  },
  {
    "name": "VerifyPass",
    "category": "Widget",
    "confidence": "high",
    "domain_signatures": [],
    "html_signatures": [],
    "script_url_signatures": [
      "cdn.id.services",
      "cdn.verifypass.com"
    ],
    "js_asset_signatures": [
      "verifypass_api_instantiator",
      "verifypass_is_loaded",
      "verifypass_popup"
    ],
    "package_url_signatures": [],
    "stylesheet_url_signatures": [],
    "meta_generator_signatures": [],
    "dom_marker_signatures": [],
    "cookie_signatures": [],
    "header_signatures": {}
  },
  {
    "name": "Verizon Media",
    "category": "Advertising",
    "confidence": "high",
    "domain_signatures": [],
    "html_signatures": [
      "pixel.advertising.com"
    ],
    "script_url_signatures": [
      "advertising.com",
      "vidible.tv"
    ],
    "js_asset_signatures": [],
    "package_url_signatures": [],
    "stylesheet_url_signatures": [],
    "meta_generator_signatures": [],
    "dom_marker_signatures": [],
    "cookie_signatures": [],
    "header_signatures": {}
  },
  {
    "name": "Very Good Security",
    "category": "Captcha",
    "confidence": "high",
    "domain_signatures": [],
    "html_signatures": [],
    "script_url_signatures": [
      "js.verygoodvault.com"
    ],
    "js_asset_signatures": [
      "VGSCollect"
    ],
    "package_url_signatures": [],
    "stylesheet_url_signatures": [],
    "meta_generator_signatures": [],
    "dom_marker_signatures": [],
    "cookie_signatures": [],
    "header_signatures": {
      "content-security-policy": [
        "verygoodvault.com"
      ]
    }
  },
  {
    "name": "Vev",
    "category": "Document Management System",
    "confidence": "high",
    "domain_signatures": [],
    "html_signatures": [],
    "script_url_signatures": [
      "vev.design"
    ],
    "js_asset_signatures": [
      "vev.App.compare",
      "vev.DEFAULT_APP_STATE"
    ],
    "package_url_signatures": [],
    "stylesheet_url_signatures": [],
    "meta_generator_signatures": [],
    "dom_marker_signatures": [],
    "cookie_signatures": [],
    "header_signatures": {}
  },
  {
    "name": "ViaBill",
    "category": "Recruitment",
    "confidence": "high",
    "domain_signatures": [],
    "html_signatures": [],
    "script_url_signatures": [
      "viabill.com"
    ],
    "js_asset_signatures": [
      "viabillOptions.state.subscriptions",
      "viabillPricetagInternal.conf.productsByLocale"
    ],
    "package_url_signatures": [],
    "stylesheet_url_signatures": [],
    "meta_generator_signatures": [],
    "dom_marker_signatures": [],
    "cookie_signatures": [],
    "header_signatures": {}
  },
  {
    "name": "Viafoura",
    "category": "Digital Asset Management",
    "confidence": "medium",
    "domain_signatures": [],
    "html_signatures": [],
    "script_url_signatures": [],
    "js_asset_signatures": [
      "dfm_viafoura_options",
      "viafoura.bootstrap",
      "viafoura.core"
    ],
    "package_url_signatures": [],
    "stylesheet_url_signatures": [],
    "meta_generator_signatures": [],
    "dom_marker_signatures": [],
    "cookie_signatures": [],
    "header_signatures": {}
  },
  {
    "name": "vibecommerce",
    "category": "Ecommerce",
    "confidence": "high",
    "domain_signatures": [],
    "html_signatures": [
      "vibecommerce"
    ],
    "script_url_signatures": [],
    "js_asset_signatures": [],
    "package_url_signatures": [],
    "stylesheet_url_signatures": [],
    "meta_generator_signatures": [
      "vibecommerce"
    ],
    "dom_marker_signatures": [],
    "cookie_signatures": [],
    "header_signatures": {}
  },
  {
    "name": "Vidazoo",
    "category": "Advertising",
    "confidence": "high",
    "domain_signatures": [],
    "html_signatures": [],
    "script_url_signatures": [
      "vidazoo.com"
    ],
    "js_asset_signatures": [
      "__vidazooPlayer__",
      "vidazoo.version"
    ],
    "package_url_signatures": [],
    "stylesheet_url_signatures": [],
    "meta_generator_signatures": [],
    "dom_marker_signatures": [],
    "cookie_signatures": [],
    "header_signatures": {}
  },
  {
    "name": "Video Greet",
    "category": "Other",
    "confidence": "medium",
    "domain_signatures": [],
    "html_signatures": [],
    "script_url_signatures": [],
    "js_asset_signatures": [
      "__vg.video_greet_button_src"
    ],
    "package_url_signatures": [],
    "stylesheet_url_signatures": [],
    "meta_generator_signatures": [],
    "dom_marker_signatures": [],
    "cookie_signatures": [],
    "header_signatures": {}
  },
  {
    "name": "Video.js",
    "category": "Video Player",
    "confidence": "high",
    "domain_signatures": [],
    "html_signatures": [
      "video-js",
      "vjs-default-skin"
    ],
    "script_url_signatures": [
      "cdn.jsdelivr.net/npm/video.js",
      "video.min.js",
      "vjs.zencdn.net"
    ],
    "js_asset_signatures": [
      "video.js",
      "videojs(",
      "videojs.registerPlugin"
    ],
    "package_url_signatures": [
      "video.js"
    ],
    "stylesheet_url_signatures": [
      "video-js.min.css",
      "vjs.zencdn.net"
    ],
    "meta_generator_signatures": [],
    "dom_marker_signatures": [
      "video-js",
      "vjs-big-play-button",
      "vjs-default-skin"
    ],
    "cookie_signatures": [],
    "header_signatures": {}
  },
  {
    "name": "VideoJS",
    "category": "Video Player",
    "confidence": "high",
    "domain_signatures": [],
    "html_signatures": [],
    "script_url_signatures": [
      "cdnjs.cloudflare.com/ajax/libs/video.js",
      "zencdn.net/c/video.js"
    ],
    "js_asset_signatures": [
      "videojs.VERSION"
    ],
    "package_url_signatures": [],
    "stylesheet_url_signatures": [],
    "meta_generator_signatures": [],
    "dom_marker_signatures": [],
    "cookie_signatures": [],
    "header_signatures": {}
  },
  {
    "name": "Vigbo",
    "category": "CMS",
    "confidence": "high",
    "domain_signatures": [],
    "html_signatures": [
      "gophotoweb.com",
      "vigbo.com"
    ],
    "script_url_signatures": [
      "gophotoweb.com",
      "vigbo.com"
    ],
    "js_asset_signatures": [],
    "package_url_signatures": [],
    "stylesheet_url_signatures": [],
    "meta_generator_signatures": [],
    "dom_marker_signatures": [],
    "cookie_signatures": [
      "_gphw_mode"
    ],
    "header_signatures": {}
  },
  {
    "name": "Vignette",
    "category": "CMS",
    "confidence": "medium",
    "domain_signatures": [],
    "html_signatures": [
      "vgn-?ext"
    ],
    "script_url_signatures": [],
    "js_asset_signatures": [],
    "package_url_signatures": [],
    "stylesheet_url_signatures": [],
    "meta_generator_signatures": [],
    "dom_marker_signatures": [],
    "cookie_signatures": [],
    "header_signatures": {}
  },
  {
    "name": "Vimeo",
    "category": "Video Player",
    "confidence": "medium",
    "domain_signatures": [],
    "html_signatures": [
      "vimeo.com"
    ],
    "script_url_signatures": [],
    "js_asset_signatures": [
      "Vimeo.Player",
      "VimeoPlayer"
    ],
    "package_url_signatures": [],
    "stylesheet_url_signatures": [],
    "meta_generator_signatures": [],
    "dom_marker_signatures": [],
    "cookie_signatures": [],
    "header_signatures": {}
  },
  {
    "name": "Vimeo OTT",
    "category": "Video Player",
    "confidence": "medium",
    "domain_signatures": [],
    "html_signatures": [],
    "script_url_signatures": [],
    "js_asset_signatures": [
      "_vhx",
      "VHX.config"
    ],
    "package_url_signatures": [],
    "stylesheet_url_signatures": [],
    "meta_generator_signatures": [],
    "dom_marker_signatures": [],
    "cookie_signatures": [],
    "header_signatures": {}
  },
  {
    "name": "Viral Loops",
    "category": "Ticket Booking",
    "confidence": "high",
    "domain_signatures": [],
    "html_signatures": [],
    "script_url_signatures": [
      "app.viral-loops.com"
    ],
    "js_asset_signatures": [],
    "package_url_signatures": [],
    "stylesheet_url_signatures": [
      "wp-content/plugins/viral-loops-wp-integration/assets"
    ],
    "meta_generator_signatures": [],
    "dom_marker_signatures": [],
    "cookie_signatures": [],
    "header_signatures": {}
  },
  {
    "name": "Virgool",
    "category": "Blog",
    "confidence": "high",
    "domain_signatures": [
      "?virgool.io"
    ],
    "html_signatures": [],
    "script_url_signatures": [],
    "js_asset_signatures": [],
    "package_url_signatures": [],
    "stylesheet_url_signatures": [],
    "meta_generator_signatures": [],
    "dom_marker_signatures": [],
    "cookie_signatures": [],
    "header_signatures": {
      "x-powered-by": [
        "Virgool"
      ]
    }
  },
  {
    "name": "Virtooal",
    "category": "Other",
    "confidence": "high",
    "domain_signatures": [],
    "html_signatures": [],
    "script_url_signatures": [
      "virtooal.com"
    ],
    "js_asset_signatures": [],
    "package_url_signatures": [],
    "stylesheet_url_signatures": [],
    "meta_generator_signatures": [],
    "dom_marker_signatures": [],
    "cookie_signatures": [],
    "header_signatures": {}
  },
  {
    "name": "Virtuagym",
    "category": "Live Chat",
    "confidence": "medium",
    "domain_signatures": [],
    "html_signatures": [
      "virtuagym.com"
    ],
    "script_url_signatures": [],
    "js_asset_signatures": [
      "open_vg_custom_modal",
      "trigger_vg_neutral_message",
      "VGTutorial"
    ],
    "package_url_signatures": [],
    "stylesheet_url_signatures": [],
    "meta_generator_signatures": [],
    "dom_marker_signatures": [],
    "cookie_signatures": [],
    "header_signatures": {}
  },
  {
    "name": "Virtual Chat",
    "category": "Page Builder",
    "confidence": "high",
    "domain_signatures": [],
    "html_signatures": [],
    "script_url_signatures": [
      "virtual-chat.co.il"
    ],
    "js_asset_signatures": [],
    "package_url_signatures": [],
    "stylesheet_url_signatures": [],
    "meta_generator_signatures": [],
    "dom_marker_signatures": [],
    "cookie_signatures": [],
    "header_signatures": {}
  },
  {
    "name": "VirtualSpirits",
    "category": "Page Builder",
    "confidence": "medium",
    "domain_signatures": [],
    "html_signatures": [],
    "script_url_signatures": [],
    "js_asset_signatures": [
      "vspiritbutton",
      "vspirits_chat_client",
      "vspiritsizeheight"
    ],
    "package_url_signatures": [],
    "stylesheet_url_signatures": [],
    "meta_generator_signatures": [],
    "dom_marker_signatures": [],
    "cookie_signatures": [],
    "header_signatures": {}
  },
  {
    "name": "VirtueMart",
    "category": "Ecommerce",
    "confidence": "medium",
    "domain_signatures": [],
    "html_signatures": [
      "vmMainPage"
    ],
    "script_url_signatures": [],
    "js_asset_signatures": [],
    "package_url_signatures": [],
    "stylesheet_url_signatures": [],
    "meta_generator_signatures": [],
    "dom_marker_signatures": [],
    "cookie_signatures": [],
    "header_signatures": {}
  },
  {
    "name": "Virtusize",
    "category": "Personalisation",
    "confidence": "high",
    "domain_signatures": [],
    "html_signatures": [],
    "script_url_signatures": [
      "virtusize.jp"
    ],
    "js_asset_signatures": [],
    "package_url_signatures": [],
    "stylesheet_url_signatures": [],
    "meta_generator_signatures": [],
    "dom_marker_signatures": [],
    "cookie_signatures": [],
    "header_signatures": {}
  },
  {
    "name": "Visa Checkout",
    "category": "Payment Processor",
    "confidence": "high",
    "domain_signatures": [],
    "html_signatures": [],
    "script_url_signatures": [
      "secure.checkout.visa.com"
    ],
    "js_asset_signatures": [],
    "package_url_signatures": [],
    "stylesheet_url_signatures": [],
    "meta_generator_signatures": [],
    "dom_marker_signatures": [],
    "cookie_signatures": [],
    "header_signatures": {}
  },
  {
    "name": "Visely",
    "category": "Other",
    "confidence": "medium",
    "domain_signatures": [],
    "html_signatures": [],
    "script_url_signatures": [],
    "js_asset_signatures": [
      "Visely.RecommendationsApi",
      "ViselyCartProductIds",
      "ViselyPage"
    ],
    "package_url_signatures": [],
    "stylesheet_url_signatures": [],
    "meta_generator_signatures": [],
    "dom_marker_signatures": [],
    "cookie_signatures": [],
    "header_signatures": {}
  },
  {
    "name": "VisiOpt",
    "category": "A/B Testing",
    "confidence": "high",
    "domain_signatures": [],
    "html_signatures": [],
    "script_url_signatures": [
      "visiopt.com"
    ],
    "js_asset_signatures": [
      "visiopt_code"
    ],
    "package_url_signatures": [],
    "stylesheet_url_signatures": [],
    "meta_generator_signatures": [],
    "dom_marker_signatures": [],
    "cookie_signatures": [],
    "header_signatures": {}
  },
  {
    "name": "Visual Composer",
    "category": "Document Management System",
    "confidence": "high",
    "domain_signatures": [],
    "html_signatures": [],
    "script_url_signatures": [],
    "js_asset_signatures": [],
    "package_url_signatures": [],
    "stylesheet_url_signatures": [],
    "meta_generator_signatures": [
      "Composer"
    ],
    "dom_marker_signatures": [],
    "cookie_signatures": [],
    "header_signatures": {}
  },
  {
    "name": "Visual Portfolio",
    "category": "Geolocation",
    "confidence": "medium",
    "domain_signatures": [],
    "html_signatures": [],
    "script_url_signatures": [],
    "js_asset_signatures": [
      "VPData.screenSizes",
      "VPData.version"
    ],
    "package_url_signatures": [],
    "stylesheet_url_signatures": [],
    "meta_generator_signatures": [],
    "dom_marker_signatures": [],
    "cookie_signatures": [],
    "header_signatures": {}
  },
  {
    "name": "Visual Quiz Builder",
    "category": "Other",
    "confidence": "high",
    "domain_signatures": [],
    "html_signatures": [],
    "script_url_signatures": [
      "d.cdn.digitaloceanspaces.com",
      "whai-cdn.nyc"
    ],
    "js_asset_signatures": [],
    "package_url_signatures": [],
    "stylesheet_url_signatures": [],
    "meta_generator_signatures": [],
    "dom_marker_signatures": [],
    "cookie_signatures": [],
    "header_signatures": {}
  },
  {
    "name": "Visualsoft",
    "category": "Ecommerce",
    "confidence": "high",
    "domain_signatures": [],
    "html_signatures": [
      "vs_status_checker_version",
      "vsvatprices"
    ],
    "script_url_signatures": [],
    "js_asset_signatures": [],
    "package_url_signatures": [],
    "stylesheet_url_signatures": [],
    "meta_generator_signatures": [],
    "dom_marker_signatures": [],
    "cookie_signatures": [
      "vscommerce"
    ],
    "header_signatures": {}
  },
  {
    "name": "Vitals",
    "category": "Other",
    "confidence": "high",
    "domain_signatures": [],
    "html_signatures": [],
    "script_url_signatures": [
      "appsolve.io"
    ],
    "js_asset_signatures": [
      "vitals_app_cache_keys_v1",
      "vitals_country_code",
      "vitals_product_data"
    ],
    "package_url_signatures": [],
    "stylesheet_url_signatures": [],
    "meta_generator_signatures": [],
    "dom_marker_signatures": [],
    "cookie_signatures": [],
    "header_signatures": {}
  },
  {
    "name": "Vite",
    "category": "Build Tool",
    "confidence": "medium",
    "domain_signatures": [],
    "html_signatures": [
      "vite/client"
    ],
    "script_url_signatures": [
      "@vite/client",
      "vite.svg"
    ],
    "js_asset_signatures": [
      "/vite.svg",
      "@vite/client",
      "__vite_is_modern_browser",
      "import.meta.env"
    ],
    "package_url_signatures": [
      "@vitejs/plugin-react",
      "@vitejs/plugin-vue",
      "vite"
    ],
    "stylesheet_url_signatures": [],
    "meta_generator_signatures": [],
    "dom_marker_signatures": [],
    "cookie_signatures": [],
    "header_signatures": {}
  },
  {
    "name": "VitePress",
    "category": "Cryptominer",
    "confidence": "medium",
    "domain_signatures": [],
    "html_signatures": [],
    "script_url_signatures": [],
    "js_asset_signatures": [
      "__VP_HASH_MAP__"
    ],
    "package_url_signatures": [],
    "stylesheet_url_signatures": [],
    "meta_generator_signatures": [],
    "dom_marker_signatures": [],
    "cookie_signatures": [],
    "header_signatures": {}
  },
  {
    "name": "Vitrin.me",
    "category": "Document Management System",
    "confidence": "high",
    "domain_signatures": [],
    "html_signatures": [],
    "script_url_signatures": [
      "vitrin.me"
    ],
    "js_asset_signatures": [],
    "package_url_signatures": [],
    "stylesheet_url_signatures": [],
    "meta_generator_signatures": [],
    "dom_marker_signatures": [],
    "cookie_signatures": [],
    "header_signatures": {}
  },
  {
    "name": "VIVVO",
    "category": "CMS",
    "confidence": "high",
    "domain_signatures": [],
    "html_signatures": [],
    "script_url_signatures": [],
    "js_asset_signatures": [],
    "package_url_signatures": [],
    "stylesheet_url_signatures": [],
    "meta_generator_signatures": [],
    "dom_marker_signatures": [],
    "cookie_signatures": [
      "VivvoSessionId"
    ],
    "header_signatures": {}
  },
  {
    "name": "Vizury",
    "category": "Marketing Automation",
    "confidence": "high",
    "domain_signatures": [],
    "html_signatures": [],
    "script_url_signatures": [
      "vizury.com"
    ],
    "js_asset_signatures": [
      "safariVizury",
      "vizury_data"
    ],
    "package_url_signatures": [],
    "stylesheet_url_signatures": [],
    "meta_generator_signatures": [],
    "dom_marker_signatures": [],
    "cookie_signatures": [],
    "header_signatures": {}
  },
  {
    "name": "VK Pixel",
    "category": "Analytics",
    "confidence": "high",
    "domain_signatures": [],
    "html_signatures": [
      "vk.com/rtrg?p=VK-RTRG-"
    ],
    "script_url_signatures": [
      "vk.com/js/api/openapi.js"
    ],
    "js_asset_signatures": [],
    "package_url_signatures": [],
    "stylesheet_url_signatures": [],
    "meta_generator_signatures": [],
    "dom_marker_signatures": [],
    "cookie_signatures": [],
    "header_signatures": {}
  },
  {
    "name": "Vnda",
    "category": "Ecommerce",
    "confidence": "medium",
    "domain_signatures": [],
    "html_signatures": [
      "cdn.vnda.com.br"
    ],
    "script_url_signatures": [],
    "js_asset_signatures": [
      "vnda.checkout",
      "Vnda.loadCartPopup"
    ],
    "package_url_signatures": [],
    "stylesheet_url_signatures": [],
    "meta_generator_signatures": [],
    "dom_marker_signatures": [],
    "cookie_signatures": [],
    "header_signatures": {}
  },
  {
    "name": "Vntana",
    "category": "Other",
    "confidence": "medium",
    "domain_signatures": [],
    "html_signatures": [
      "embed.vntana.com"
    ],
    "script_url_signatures": [],
    "js_asset_signatures": [],
    "package_url_signatures": [],
    "stylesheet_url_signatures": [],
    "meta_generator_signatures": [],
    "dom_marker_signatures": [],
    "cookie_signatures": [],
    "header_signatures": {}
  },
  {
    "name": "Volusion",
    "category": "Ecommerce",
    "confidence": "high",
    "domain_signatures": [],
    "html_signatures": [
      "data-vn-page-name"
    ],
    "script_url_signatures": [
      "volusion.js"
    ],
    "js_asset_signatures": [
      "volusion"
    ],
    "package_url_signatures": [],
    "stylesheet_url_signatures": [],
    "meta_generator_signatures": [],
    "dom_marker_signatures": [],
    "cookie_signatures": [],
    "header_signatures": {}
  },
  {
    "name": "Vonage Video API",
    "category": "Other",
    "confidence": "high",
    "domain_signatures": [],
    "html_signatures": [],
    "script_url_signatures": [
      "opentok.com"
    ],
    "js_asset_signatures": [],
    "package_url_signatures": [],
    "stylesheet_url_signatures": [],
    "meta_generator_signatures": [],
    "dom_marker_signatures": [],
    "cookie_signatures": [],
    "header_signatures": {}
  },
  {
    "name": "Voog.com Website Builder",
    "category": "CMS",
    "confidence": "high",
    "domain_signatures": [],
    "html_signatures": [
      "voog.com/tracker.js"
    ],
    "script_url_signatures": [
      "voog.com/tracker.js"
    ],
    "js_asset_signatures": [],
    "package_url_signatures": [],
    "stylesheet_url_signatures": [],
    "meta_generator_signatures": [],
    "dom_marker_signatures": [],
    "cookie_signatures": [],
    "header_signatures": {}
  },
  {
    "name": "Voracio",
    "category": "Ecommerce",
    "confidence": "high",
    "domain_signatures": [],
    "html_signatures": [],
    "script_url_signatures": [],
    "js_asset_signatures": [],
    "package_url_signatures": [],
    "stylesheet_url_signatures": [],
    "meta_generator_signatures": [],
    "dom_marker_signatures": [],
    "cookie_signatures": [
      "voracio_csrf_token",
      "voracio_sessionid"
    ],
    "header_signatures": {}
  },
  {
    "name": "VP-ASP",
    "category": "Ecommerce",
    "confidence": "high",
    "domain_signatures": [],
    "html_signatures": [
      "VP-ASP"
    ],
    "script_url_signatures": [
      "vs350.js"
    ],
    "js_asset_signatures": [],
    "package_url_signatures": [],
    "stylesheet_url_signatures": [],
    "meta_generator_signatures": [],
    "dom_marker_signatures": [],
    "cookie_signatures": [],
    "header_signatures": {}
  },
  {
    "name": "VTEX",
    "category": "Ecommerce",
    "confidence": "high",
    "domain_signatures": [],
    "html_signatures": [
      "vteximg.com.br"
    ],
    "script_url_signatures": [],
    "js_asset_signatures": [],
    "package_url_signatures": [],
    "stylesheet_url_signatures": [
      "vteximg.com.br"
    ],
    "meta_generator_signatures": [],
    "dom_marker_signatures": [],
    "cookie_signatures": [
      "vtex_session",
      "VtexFingerPrint",
      "VtexStoreVersion",
      "VtexWorkspace"
    ],
    "header_signatures": {
      "powered": [
        "vtex"
      ],
      "server": [
        "VTEX"
      ]
    }
  },
  {
    "name": "Vtiger",
    "category": "Live Chat",
    "confidence": "medium",
    "domain_signatures": [],
    "html_signatures": [],
    "script_url_signatures": [],
    "js_asset_signatures": [
      "Vtiger_Base_Js",
      "Vtiger_Helper_Js"
    ],
    "package_url_signatures": [],
    "stylesheet_url_signatures": [],
    "meta_generator_signatures": [],
    "dom_marker_signatures": [],
    "cookie_signatures": [],
    "header_signatures": {}
  },
  {
    "name": "Vue Storefront",
    "category": "Other",
    "confidence": "high",
    "domain_signatures": [],
    "html_signatures": [],
    "script_url_signatures": [
      "vsf-layout"
    ],
    "js_asset_signatures": [],
    "package_url_signatures": [],
    "stylesheet_url_signatures": [],
    "meta_generator_signatures": [
      "Storefront",
      "Vue"
    ],
    "dom_marker_signatures": [],
    "cookie_signatures": [],
    "header_signatures": {}
  },
  {
    "name": "Vue.ai",
    "category": "Personalisation",
    "confidence": "high",
    "domain_signatures": [],
    "html_signatures": [],
    "script_url_signatures": [
      "vue_ai.js",
      "vuex.vue.ai"
    ],
    "js_asset_signatures": [
      "getVueUrlSegments"
    ],
    "package_url_signatures": [],
    "stylesheet_url_signatures": [],
    "meta_generator_signatures": [],
    "dom_marker_signatures": [],
    "cookie_signatures": [],
    "header_signatures": {}
  },
  {
    "name": "Vue.js",
    "category": "JavaScript Framework",
    "confidence": "medium",
    "domain_signatures": [],
    "html_signatures": [
      "__vue__",
      "sdata-v",
      "vue.js"
    ],
    "script_url_signatures": [
      "cdn.jsdelivr.net/npm/vue",
      "cdnjs.cloudflare.com/ajax/libs/vue",
      "unpkg.com/vue"
    ],
    "js_asset_signatures": [
      "__VUE__",
      "__VUE_HOT_MAP__",
      "data-v-",
      "vue-router",
      "Vue.createApp",
      "Vue.version"
    ],
    "package_url_signatures": [
      "pinia",
      "vue",
      "vue-router"
    ],
    "stylesheet_url_signatures": [],
    "meta_generator_signatures": [],
    "dom_marker_signatures": [
      "data-v-"
    ],
    "cookie_signatures": [],
    "header_signatures": {}
  },
  {
    "name": "VuePress",
    "category": "Cryptominer",
    "confidence": "high",
    "domain_signatures": [],
    "html_signatures": [],
    "script_url_signatures": [],
    "js_asset_signatures": [
      "__VUEPRESS__.version"
    ],
    "package_url_signatures": [],
    "stylesheet_url_signatures": [],
    "meta_generator_signatures": [
      "VuePress"
    ],
    "dom_marker_signatures": [],
    "cookie_signatures": [],
    "header_signatures": {}
  },
  {
    "name": "Vuex",
    "category": "User Onboarding",
    "confidence": "medium",
    "domain_signatures": [],
    "html_signatures": [],
    "script_url_signatures": [],
    "js_asset_signatures": [
      "Vuex.version"
    ],
    "package_url_signatures": [],
    "stylesheet_url_signatures": [],
    "meta_generator_signatures": [],
    "dom_marker_signatures": [],
    "cookie_signatures": [],
    "header_signatures": {}
  },
  {
    "name": "VuFind",
    "category": "Search Engine",
    "confidence": "high",
    "domain_signatures": [],
    "html_signatures": [],
    "script_url_signatures": [],
    "js_asset_signatures": [
      "VuFind.defaultSearchBackend"
    ],
    "package_url_signatures": [],
    "stylesheet_url_signatures": [],
    "meta_generator_signatures": [
      "VuFind"
    ],
    "dom_marker_signatures": [],
    "cookie_signatures": [],
    "header_signatures": {}
  },
  {
    "name": "VWO",
    "category": "Analytics",
    "confidence": "high",
    "domain_signatures": [],
    "html_signatures": [],
    "script_url_signatures": [
      "dev.visualwebsiteoptimizer.com",
      "visual-website-optimizer"
    ],
    "js_asset_signatures": [
      "__vwo",
      "_vwo_code",
      "_vwo_settings_timer"
    ],
    "package_url_signatures": [],
    "stylesheet_url_signatures": [],
    "meta_generator_signatures": [],
    "dom_marker_signatures": [],
    "cookie_signatures": [],
    "header_signatures": {}
  },
  {
    "name": "VWO Engage",
    "category": "Marketing Automation",
    "confidence": "high",
    "domain_signatures": [],
    "html_signatures": [],
    "script_url_signatures": [
      "cdn.pushcrew"
    ],
    "js_asset_signatures": [
      "_pushcrewDebuggingQueue"
    ],
    "package_url_signatures": [],
    "stylesheet_url_signatures": [],
    "meta_generator_signatures": [],
    "dom_marker_signatures": [],
    "cookie_signatures": [],
    "header_signatures": {}
  },
  {
    "name": "vxe-table",
    "category": "User Onboarding",
    "confidence": "medium",
    "domain_signatures": [],
    "html_signatures": [],
    "script_url_signatures": [],
    "js_asset_signatures": [],
    "package_url_signatures": [],
    "stylesheet_url_signatures": [],
    "meta_generator_signatures": [],
    "dom_marker_signatures": [
      "vxe-table"
    ],
    "cookie_signatures": [],
    "header_signatures": {}
  }
]
